qstress/__about__.py
qstress/cache.py
qstress/cli.py
qstress/config.py
qstress/globals.py
qstress/util.py
qstress-1.0.1.dist-info/METADATA
qstress-1.0.1.dist-info/WHEEL
qstress-1.0.1.dist-info/entry_points.txt
qstress-1.0.1.dist-info/licenses/LICENSE.txt
qstress-1.0.1.dist-info/RECORD
